redshift_credentials_manager/__init__.py
redshift_credentials_manager/connectors.py
redshift_credentials_manager/manager.py
redshift_credentials_manager-3.0.5.dist-info/METADATA
redshift_credentials_manager-3.0.5.dist-info/WHEEL
redshift_credentials_manager-3.0.5.dist-info/top_level.txt
redshift_credentials_manager-3.0.5.dist-info/RECORD
